text_tracker/__init__.py
text_tracker/text_tracker.py
text_tracker-1.0.1.dist-info/LICENSE
text_tracker-1.0.1.dist-info/METADATA
text_tracker-1.0.1.dist-info/WHEEL
text_tracker-1.0.1.dist-info/top_level.txt
text_tracker-1.0.1.dist-info/RECORD
