Metadata-Version: 2.1
Name: text-tracker
Version: 1.0.1
Summary: Keep track of text locations!
Home-page: https://github.com/supercooper6558/Text-Tracker
Author: Cooper Sanders
Author-email: tromboneguy@coopersanders.com
License: UNKNOWN
Platform: UNKNOWN
Classifier: Programming Language :: Python :: 3
Classifier: License :: OSI Approved :: MIT License
Classifier: Operating System :: OS Independent
Requires-Python: >=3.6
